wechat_msg/WeChat.py
wechat_msg/__init__.py
wechat_msg-0.5.dist-info/LICENSE
wechat_msg-0.5.dist-info/METADATA
wechat_msg-0.5.dist-info/WHEEL
wechat_msg-0.5.dist-info/top_level.txt
wechat_msg-0.5.dist-info/RECORD
