Metadata-Version: 2.1
Name: wechat-msg
Version: 0.5
Summary: wechat send message
Home-page: https://github.com/wnma3mz/wechat_msg
Author: wnma3mz
Author-email: 
License: UNKNOWN
Platform: UNKNOWN
Classifier: Programming Language :: Python :: 3
Classifier: License :: OSI Approved :: MIT License
Classifier: Operating System :: OS Independent
Requires-Dist: requests (>=2.20.0)
